app/__init__.py
app/cli.py
app/main.py
app/models/__init__.py
app/models/task.py
app/repositories/__init__.py
app/repositories/taskRepository.py
app/services/__init__.py
app/services/taskService.py
app/util/__init__.py
app/util/taskHelper.py
test/__init__.py
test/test_cli.py
tasksu-1.0.2.dist-info/LICENSE
tasksu-1.0.2.dist-info/METADATA
tasksu-1.0.2.dist-info/WHEEL
tasksu-1.0.2.dist-info/entry_points.txt
tasksu-1.0.2.dist-info/top_level.txt
tasksu-1.0.2.dist-info/RECORD
