Metadata-Version: 2.1
Name: tasksu
Version: 1.0.2
Summary: A Task Management CLI Application.
Home-page: https://github.com/zephyr834/tasksu
Author: Cory
Author-email: tacocat8345@gmail.com
Classifier: Programming Language :: Python :: 3
Classifier: License :: OSI Approved :: MIT License
Classifier: Operating System :: OS Independent
Requires-Python: >=3.6
License-File: LICENSE
Requires-Dist: click==8.1.7
